chainfury_server/__init__.py
chainfury_server/api/__init__.py
chainfury_server/api/chains.py
chainfury_server/api/prompts.py
chainfury_server/api/user.py
chainfury_server/app.py
chainfury_server/database.py
chainfury_server/engines/__init__.py
chainfury_server/engines/fury.py
chainfury_server/engines/registry.py
chainfury_server/examples/cf_chuck_norris.json
chainfury_server/examples/cf_serper_summarizer.json
chainfury_server/examples/index.json
chainfury_server/examples/lf_basic_template.json
chainfury_server/landing.py
chainfury_server/server.py
chainfury_server/static/assets/Button-a96cea0a.js
chainfury_server/static/assets/ChatComp-71be8e8d.js
chainfury_server/static/assets/Close-24a83598.js
chainfury_server/static/assets/Sidebar-554b7d1a.js
chainfury_server/static/assets/index-063983b4.js
chainfury_server/static/assets/index-10efa1c9.js
chainfury_server/static/assets/index-22b1801a.js
chainfury_server/static/assets/index-57a158a9.css
chainfury_server/static/assets/index-57f9da2e.js
chainfury_server/static/assets/index-63e96811.js
chainfury_server/static/assets/index-7a81f9ea.js
chainfury_server/static/assets/index-d483e673.css
chainfury_server/static/assets/store-43bbd427.js
chainfury_server/static/assets/useControlled-235581b1.js
chainfury_server/static/chainfury.png
chainfury_server/static/index.html
chainfury_server/static/script/embedBot.js
chainfury_server/utils.py
chainfury_server/version.py
chainfury_server-2.0.2.dist-info/METADATA
chainfury_server-2.0.2.dist-info/WHEEL
chainfury_server-2.0.2.dist-info/entry_points.txt
chainfury_server-2.0.2.dist-info/RECORD
